abess.libs/libgomp-65f46eca.so.1.0.0
abess-0.4.8.dist-info/LICENSE
abess-0.4.8.dist-info/METADATA
abess-0.4.8.dist-info/RECORD
abess-0.4.8.dist-info/top_level.txt
abess-0.4.8.dist-info/WHEEL
abess/decomposition.py
abess/pybind_cabess.cpython-310-i386-linux-gnu.so
abess/pca.py
abess/functions.py
abess/datasets.py
abess/utilities.py
abess/__init__.py
abess/bess_base.py
abess/linear.py
