Metadata-Version: 2.1
Name: abess
Version: 0.4.8
Summary: abess: Fast Best Subset Selection
Home-page: https://abess.readthedocs.io
Author: Jin Zhu, Kangkang Jiang, 
Author-email: zhuj37@mail2.sysu.edu.cn
Maintainer: Junhao Huang
Maintainer-email: huangjh256@mail2.sysu.edu.cn
License: GPL-3
Download-URL: https://pypi.python.org/pypi/abess
Project-URL: Bug Tracker, https://github.com/abess-team/abess/issues
Project-URL: Documentation, https://abess.readthedocs.io
Project-URL: Source Code, https://github.com/abess-team/abess
Platform: UNKNOWN
Classifier: Intended Audience :: Science/Research
Classifier: Intended Audience :: Developers
Classifier: Programming Language :: C++
Classifier: Programming Language :: Python
Classifier: Topic :: Software Development
Classifier: Topic :: Scientific/Engineering
Classifier: Topic :: Scientific/Engineering :: Artificial Intelligence
Classifier: Topic :: Scientific/Engineering :: Mathematics
Classifier: Operating System :: Microsoft :: Windows
Classifier: Operating System :: POSIX :: Linux
Classifier: Operating System :: MacOS
Classifier: Programming Language :: Python
Classifier: Programming Language :: Python :: 3.6
Classifier: Programming Language :: Python :: 3.7
Classifier: Programming Language :: Python :: 3.8
Classifier: Programming Language :: Python :: 3.9
Classifier: Programming Language :: Python :: 3.10
Classifier: Programming Language :: Python :: 3.11
Requires-Python: >=3.6
License-File: LICENSE
Requires-Dist: numpy
Requires-Dist: pandas
Requires-Dist: scipy
Requires-Dist: scikit-learn (>=0.24)
